{"version":3,"kind":"Article","sha256":"962627692afb068b24202d63fce22aeba832d1618f6fe6c6139299c54957ec5e","slug":"1-1-6","location":"/e/parent_2/part_1/1-1.md","dependencies":[],"frontmatter":{"title":"1-1","numbering":{"title":{"offset":3}},"exports":[{"format":"md","filename":"1-1.md","url":"/JB_template/build/1-1-75365db96b2779b0fb9f46621802b811.md"}]},"mdast":{"type":"root","children":[],"key":"fHQIWjmNOR"},"references":{"cite":{"order":[],"data":{}}},"footer":{"navigation":{"prev":{"title":"3-1","url":"/3-1-5","group":"Part 3"},"next":{"title":"2-1","url":"/2-1-6","group":"Part 2"}}},"domain":"http://localhost:3000"}