{"version":3,"kind":"Notebook","sha256":"5bbb5ce1c023855a9d1b7931a1bc228de1b913e7c09a9ada6432be6237cde50e","slug":"1-1-1","location":"/c/parent_2/part_1/1-1.ipynb","dependencies":[],"frontmatter":{"title":"Parent 2 - Part 1 - Section 1","content_includes_title":false,"numbering":{"title":{"offset":3}},"exports":[{"format":"ipynb","filename":"1-1.ipynb","url":"/JB_template/build/1-1-509d70bbba1a69b1b3ea73721daf21f0.ipynb"}]},"widgets":{},"mdast":{"type":"root","children":[{"type":"block","kind":"notebook-content","children":[{"type":"paragraph","position":{"start":{"line":3,"column":1},"end":{"line":3,"column":1}},"children":[{"type":"text","value":"Placeholder notebook for content.","position":{"start":{"line":3,"column":1},"end":{"line":3,"column":1}},"key":"UcHUoyZPkE"}],"key":"KqmytSAcVU"}],"key":"kXjAY7Ow4V"}],"key":"SnGvxa6Tj8"},"references":{"cite":{"order":[],"data":{}}},"footer":{"navigation":{"prev":{"title":"3-1","url":"/3-1","group":"Part 3"},"next":{"title":"Advanced Topics","url":"/1-1-2","group":"Part 1"}}},"domain":"http://localhost:3000"}