{"version":3,"kind":"Article","sha256":"db8087d48b75cce4336a48ac6ad957ea1a110176f1a8d4847d86f5b836eb21a2","slug":"2-2","location":"/content/parent_1/part_2/2-2.md","dependencies":[],"frontmatter":{"title":"2-2","numbering":{"title":{"offset":3}},"exports":[{"format":"md","filename":"2-2.md","url":"/2-2-e6dca418b6fc0be85ddcca64acbad540.md"}]},"mdast":{"type":"root","children":[{"type":"block","children":[{"type":"paragraph","position":{"start":{"line":5,"column":1},"end":{"line":5,"column":1}},"children":[{"type":"text","value":"part-2-second-child","position":{"start":{"line":5,"column":1},"end":{"line":5,"column":1}},"key":"jbJng2JOu6"}],"key":"PdNL2B7YPi"}],"key":"vQX8xONjGl"}],"key":"amfUbzb7E9"},"references":{"cite":{"order":[],"data":{}}}}